src/verification/alu_reference_model.v
module alu_reference_model(
	input CLK, RST,
	input CE,
	input [1:0]INP_VALID,
    input [7:0] OPA, OPB,
    input CIN, MODE,
    input [3:0] CMD,
    output reg [16:0] RES,
    output reg COUT, OFLOW, G, E, L, ERR
);

    reg [7:0] OPA_1, OPB_1;

    always @(*) begin
        // Default values
        RES = 9'b0;
        COUT = 1'b0;
        OFLOW = 1'b0;
        G = 1'b0;
        E = 1'b0;
        L = 1'b0;
        ERR = 1'b0;

		if (RST)
		begin
        	RES = 9'b0;
        	COUT = 1'b0;
        	OFLOW = 1'b0;
        	G = 1'b0;
        	E = 1'b0;
        	L = 1'b0;
        	ERR = 1'b0;
		end
		else
		if (CE)
		begin
        if (MODE) begin  // Arithmetic Mode
            case(CMD)
                4'b0000: begin  // ADD
                    {COUT,RES[7:0]} = OPA + OPB;
                end
                4'b0001: begin  // SUB
                    OFLOW = (OPA < OPB);
                    RES = OPA - OPB;
                end
                4'b0010: begin  // ADD_CIN
                    {COUT,RES[7:0]} = OPA + OPB + CIN;
                end
                4'b0011: begin  // SUB_CIN
                    OFLOW = (OPA < OPB);
                    RES = OPA - OPB - CIN;
                end
                4'b0100: RES = OPA + 1;  // INC_A
                4'b0101: RES = OPA - 1;  // DEC_A
                4'b0110: RES = OPB + 1;  // INC_B
                4'b0111: RES = OPB - 1;  // DEC_B
                4'b1000: begin  // CMP
                    RES = 9'bz;
                    if (OPA == OPB) begin
                        E = 1'b1; G = 1'b0; L = 1'b0;
                    end else if (OPA > OPB) begin
                        E = 1'b0; G = 1'b1; L = 1'b0;
                    end else begin
                        E = 1'b0; G = 1'b0; L = 1'b1;
                    end
                end
            endcase
        end 
        else begin  // Logical Mode
            case(CMD)
                4'b0000: RES = {8'b0, OPA & OPB};       // AND
                4'b0001: RES = {8'b0, ~(OPA & OPB)};    // NAND
                4'b0010: RES = {8'b0, OPA | OPB};       // OR
                4'b0011: RES = {8'b0, ~(OPA | OPB)};    // NOR
                4'b0100: RES = {8'b0, OPA ^ OPB};       // XOR
                4'b0101: RES = {8'b0, ~(OPA ^ OPB)};    // XNOR
                4'b0110: RES = {8'b0, ~OPA};            // NOT_A
                4'b0111: RES = {8'b0, ~OPB};            // NOT_B
                4'b1000: RES = {8'b0, OPA >> 1};        // SHR1_A
                4'b1001: RES = {8'b0, OPA << 1};        // SHL1_A
                4'b1010: RES = {8'b0, OPB >> 1};        // SHR1_B
                4'b1011: RES = {8'b0, OPB << 1};        // SHL1_B
                4'b1100: begin  // ROL_A_B
                    OPA_1 = OPB[0] ? {OPA[6:0], OPA[7]} : OPA;
                    OPB_1 = OPB[1] ? {OPA_1[5:0], OPA_1[7:6]} : OPA_1;
                    RES = OPB[2] ? {OPB_1[3:0], OPB_1[7:4]} : OPB_1;
                    ERR = (OPB[4] | OPB[5] | OPB[6] | OPB[7]);
                end
                4'b1101: begin  // ROR_A_B
                    OPA_1 = OPB[0] ? {OPA[0], OPA[7:1]} : OPA;
                    OPB_1 = OPB[1] ? {OPA_1[1:0], OPA_1[7:2]} : OPA_1;
                    RES = OPB[2] ? {OPB_1[3:0], OPB_1[7:4]} : OPB_1;
                    ERR = (OPB[4] | OPB[5] | OPB[6] | OPB[7]);
                end
            endcase
        end
    end
end

endmodule

src/verification/Eight_bit_ALU_rtl_design.v
//`timescale 1ns / 1ps

module Eight_bit_ALU_rtl_design #(
    parameter width = 8, 
    parameter cmd_width = 4, 
    parameter out_width = 2*width 
) (
    input [(width-1):0] OPA, OPB,
    input CLK, RST, CE, MODE, CIN,
    input [1:0] inp_valid,
    input [(cmd_width-1):0] CMD,
    
    output reg [(out_width-1):0] RES,
    output reg COUT, OFLOW, G, E, L, ERR
);
    
    reg signed [(out_width-1):0] temp_signed;
    reg [(out_width-1):0] temp_res;
    reg temp_cout, temp_oflow, temp_g, temp_e, temp_l, temp_err;
    reg signed [width-1:0] A_signed, B_signed;
    integer count = 1;
    integer count1 = 1;

    
    always @(posedge CLK or posedge RST) begin
        if (RST) begin
            RES <= 0; COUT <= 0; OFLOW <= 0; G <= 0; E <= 0; L <= 0; ERR <= 0;
        end else if (CE) begin
            if (MODE && (CMD == 4'b1001)) begin
                if (count == 3) begin 
                RES <= temp_res; 
                ERR <= temp_err; end
                else if(count == 2) 
                RES <= {out_width{1'bx}};
            end 
            else if (MODE && (CMD == 4'b1010)) begin
                if (count1 == 3) begin 
                RES <= temp_res;
                 ERR <= temp_err; end
                else if(count1 == 2) 
                RES <= {out_width{1'bx}};
            end
            
            else begin
                RES   <= temp_res;
                COUT  <= temp_cout;
                OFLOW <= temp_oflow;
                G     <= temp_g;
                E     <= temp_e;
                L     <= temp_l;
                ERR   <= temp_err;
            end
        end
    end

    always @(*) begin
        temp_res = 0;
         temp_cout = 0;
          temp_oflow = 0;
        temp_g = 0;
         temp_e = 0; 
         temp_l = 0; 
         temp_err = 0;
        temp_signed = 0;
        A_signed = 0;
         B_signed = 0;

        if (MODE) begin
            case (CMD)
                4'b0000: begin // CMD 0: ADD
                    if(inp_valid == 2'b11) begin
                        temp_res = OPA + OPB;
                        temp_cout = temp_res[width]; 
                    end else temp_err = 1'b1;
                end
                
                4'b0001: begin // CMD 1: SUB
                    if(inp_valid == 2'b11) begin
                        temp_res = OPA - OPB;
                        temp_oflow = (OPA < OPB);
                    end else temp_err = 1'b1;
                end
                
                4'b0010: begin // CMD 2: ADD_CIN
                    if(inp_valid == 2'b11) begin
                        temp_res = OPA + OPB + CIN;
                        temp_cout = temp_res[width];
                    end else temp_err = 1'b1;
                end
                
                4'b0011: begin // CMD 3: SUB_CIN
                    if(inp_valid == 2'b11) begin
                        temp_res = OPA - OPB - CIN;
                        temp_oflow = (OPA < (OPB + CIN));
                    end else temp_err = 1'b1;
                end
                4'b0100: if(inp_valid[0]) 
                            temp_res = OPA + 1'b1;
                        else 
                            temp_err = 1'b1;
                4'b0101: if(inp_valid[0]) 
                            temp_res = OPA - 1'b1;
                        else
                            temp_err = 1'b1;
                4'b0110: if(inp_valid[1])
                            temp_res = OPB + 1'b1;
                        else
                            temp_err = 1'b1;
                4'b0111: if(inp_valid[1])
                            temp_res = OPB - 1'b1;
                        else
                            temp_err = 1'b1;
                4'b1000: if(inp_valid == 2'b11) begin
                            temp_e = (OPA == OPB); 
                            temp_g = (OPA > OPB); 
                            temp_l = (OPA < OPB);
                         end 
                        else
                            temp_err = 1'b1;
                4'b1001: if(inp_valid == 2'b11) 
                                temp_res = (OPA + 1'b1) * (OPB + 1'b1); 
                            else
                                temp_err = 1'b1;
                4'b1010: if(inp_valid == 2'b11) 
                                temp_res = (OPA << 1) * OPB;
                            else
                                temp_err = 1'b1;
                4'b1011: if(inp_valid == 2'b11) begin 
                            A_signed = OPA; 
                            B_signed = OPB;
                            temp_signed = A_signed + B_signed;
                             temp_res = temp_signed;
                            temp_oflow = temp_res[width-1];
                            temp_e = (A_signed == B_signed);
                             temp_l = (A_signed < B_signed);
                              temp_g = (A_signed > B_signed);
                         end 
                         else
                             temp_err = 1'b1;
                4'b1100: if(inp_valid == 2'b11) begin 
                            A_signed = OPA;
                             B_signed = OPB;
                            temp_signed = A_signed - B_signed; 
                            temp_res = temp_signed;
                            temp_oflow = temp_res[width-1];
                            temp_e = (A_signed == B_signed);
                            temp_l = (A_signed < B_signed);
                            temp_g = (A_signed > B_signed);
                         end
                          else 
                            temp_err = 1'b1;
                default: temp_err = 1'b1;
            endcase
        end 
        else begin
            case (CMD)
                4'b0000: if(inp_valid == 2'b11) 
                             temp_res = {{width{1'b0}}, OPA & OPB};
                         else
                             temp_err = 1'b1;
                4'b0001: if(inp_valid == 2'b11)
                             temp_res = {{width{1'b0}}, ~(OPA & OPB)}; 
                         else
                             temp_err = 1'b1;
                4'b0010: if(inp_valid == 2'b11)
                             temp_res = {{width{1'b0}}, OPA | OPB};
                         else   
                             temp_err = 1'b1;
                4'b0011: if(inp_valid == 2'b11)
                             temp_res = {{width{1'b0}}, ~(OPA | OPB)};
                         else
                             temp_err = 1'b1;
                4'b0100: if(inp_valid == 2'b11) 
                             temp_res = {{width{1'b0}}, OPA ^ OPB};
                         else
                             temp_err = 1'b1;
                4'b0101: if(inp_valid == 2'b11)
                             temp_res = {{width{1'b0}}, ~(OPA ^ OPB)};
                         else
                             temp_err = 1'b1;
                4'b0110: if(inp_valid[0])
                             temp_res = {{width{1'b0}}, ~OPA};
                         else   
                             temp_err = 1'b1;
                4'b0111: if(inp_valid[1])
                             temp_res = {{width{1'b0}}, ~OPB}; 
                         else
                             temp_err = 1'b1;
                4'b1000: if(inp_valid[0])
                             temp_res = {{width{1'b0}}, OPA >> 1};
                         else
                             temp_err = 1'b1;
                4'b1001: if(inp_valid[0])
                             temp_res = {{width{1'b0}}, OPA << 1}; 
                        else
                             temp_err = 1'b1;
                4'b1010: if(inp_valid[1])
                             temp_res = {{width{1'b0}}, OPB >> 1};
                        else
                             temp_err = 1'b1;
                4'b1011: if(inp_valid[1])
                             temp_res = {{width{1'b0}}, OPB << 1};
                        else    
                             temp_err = 1'b1;
                4'b1100: if(inp_valid == 2'b11) begin
                            if (|OPB[(width-1):3]) temp_err = 1'b1; 
                            else temp_res = {{width{1'b0}}, (OPA << OPB[2:0]) | (OPA >> (width - OPB[2:0]))};
                         end else temp_err = 1'b1;
                4'b1101: if(inp_valid == 2'b11) begin
                            if (|OPB[(width-1):3]) temp_err = 1'b1; 
                            else temp_res = {{width{1'b0}}, (OPA >> OPB[2:0]) | (OPA << (width - OPB[2:0]))};
                         end else temp_err = 1'b1;
                default: temp_err = 1'b1;
            endcase
        end
    end

    always @(posedge CLK or posedge RST) begin
        if (RST) count <= 1;
        else if (CE && MODE && CMD == 4'b1001)
             count <= (count >= 3) ? 1 : count + 1;
        else count <= 1;
    end

    always @(posedge CLK or posedge RST) begin
        if (RST) count1 <= 1;
        else if (CE && MODE && CMD == 4'b1010)
             count1 <= (count1 >= 3) ? 1 : count1 + 1;
        else count1 <= 1;
    end

endmodule

src/verification/alu_testbench.v
`timescale 1ns/1ps

module alu_testbench;

    // DUT signals
    reg [7:0] OPA, OPB;
    reg CLK, RST, CE, MODE, CIN;
    reg [3:0] CMD;
    wire [15:0] RES_dut;
    wire COUT_dut, OFLOW_dut, G_dut, E_dut, L_dut, ERR_dut;

    // Reference model signals
    wire [8:0] RES_ref;
    wire COUT_ref, OFLOW_ref, G_ref, E_ref, L_ref, ERR_ref;

    // Test counters
    integer pass_count = 0;
    integer fail_count = 0;
    integer test_count = 0;

    // DUT instantiation
    Eight_bit_ALU_rtl_design dut (
        .OPA(OPA), .OPB(OPB), .CIN(CIN),
        .CLK(CLK), .RST(RST), .CMD(CMD),
        .CE(CE), .MODE(MODE),
		.inp_valid(INP_VALID),
        .COUT(COUT_dut), .OFLOW(OFLOW_dut),
        .RES(RES_dut),
        .G(G_dut), .E(E_dut), .L(L_dut),
        .ERR(ERR_dut)
    );

    // Reference model instantiation
    alu_reference_model ref (
		.CLK(CLK), .RST(RST), .CE(CE),
        .OPA(OPA), .OPB(OPB), .CIN(CIN),
        .MODE(MODE), .CMD(CMD),
		.INP_VALID(INP_VALID),
        .RES(RES_ref),
        .COUT(COUT_ref), .OFLOW(OFLOW_ref),
        .G(G_ref), .E(E_ref), .L(L_ref),
        .ERR(ERR_ref)
    );

    // Clock generation
    initial begin
        CLK = 0;
        forever #5 CLK = ~CLK;
    end

    // Test stimulus
    initial begin
        // Initialize

        RST = 1; CE = 0; CIN = 0;
        OPA = 0; OPB = 0; MODE = 0; CMD = 0;
        
        @(posedge CLK);
		begin	RST = 0; 	CE = 1;	end  // Release reset
        
		@(posedge CLK);

        // Test Arithmetic Operations
        $display("\n=== Testing Arithmetic Operations (MODE=1) ===");
        MODE = 1;
        test_arithmetic();

        // Test Logical Operations
        $display("\n=== Testing Logical Operations (MODE=0) ===");
        MODE = 0;
        test_logical();

        // Summary
        $display("\n=== TEST SUMMARY ===");
        $display("Total Tests: %0d", test_count);
        $display("PASS: %0d", pass_count);
        $display("FAIL: %0d", fail_count);
        
        if (fail_count == 0)
            $display("\n*** ALL TESTS PASSED ***\n");
        else
            $display("\n*** SOME TESTS FAILED ***\n");

        #200;
        $finish;
    end

    // Test arithmetic operations
    task test_arithmetic();
        begin
            // ADD
            apply_test(8'h0F, 8'h11, 4'b0000, "ADD");
            apply_test(8'hFF, 8'h01, 4'b0000, "ADD (overflow)");
            
            // SUB
            apply_test(8'h20, 8'h10, 4'b0001, "SUB");
            apply_test(8'h10, 8'h20, 4'b0001, "SUB (underflow)");
            
            // ADD_CIN
            CIN = 1;
            apply_test(8'h10, 8'h20, 4'b0010, "ADD_CIN");
            CIN = 0;
            
            // INC_A, DEC_A
            apply_test(8'h0A, 8'h00, 4'b0100, "INC_A");
            apply_test(8'h0A, 8'h00, 4'b0101, "DEC_A");
            
            // CMP
            apply_test(8'h10, 8'h10, 4'b1000, "CMP (equal)");
            apply_test(8'h20, 8'h10, 4'b1000, "CMP (greater)");
            apply_test(8'h10, 8'h20, 4'b1000, "CMP (less)");
        end
    endtask

    // Test logical operations
    task test_logical();
        begin
            apply_test(8'hF0, 8'h0F, 4'b0000, "AND");
            apply_test(8'hF0, 8'h0F, 4'b0001, "NAND");
            apply_test(8'hF0, 8'h0F, 4'b0010, "OR");
            apply_test(8'hF0, 8'h0F, 4'b0011, "NOR");
            apply_test(8'hAA, 8'h55, 4'b0100, "XOR");
            apply_test(8'hAA, 8'h55, 4'b0101, "XNOR");
            apply_test(8'hF0, 8'h00, 4'b0110, "NOT_A");
            apply_test(8'h00, 8'hF0, 4'b0111, "NOT_B");
            apply_test(8'hAA, 8'h00, 4'b1000, "SHR1_A");
            apply_test(8'h55, 8'h00, 4'b1001, "SHL1_A");
            apply_test(8'hAA, 8'h03, 4'b1100, "ROL_A_B");
            apply_test(8'hAA, 8'h02, 4'b1101, "ROR_A_B");
        end
    endtask

    // Apply test and check
    task apply_test(
        input [7:0] a, b,
        input [3:0] cmd,
        input [80*8:1] test_name
    );
        begin
            @(posedge CLK);
            OPA = a;
            OPB = b;
            CMD = cmd;
            
            @(posedge CLK);
            @(posedge CLK);
            
            test_count = test_count + 1;
            
            if (compare_outputs(1'b0)) begin
                $display("[PASS] %s: OPA=0x%h OPB=0x%h CMD=0x%h", 
                         test_name, a, b, cmd);
                pass_count = pass_count + 1;
            end else begin
                $display("[FAIL] %s: OPA=0x%h OPB=0x%h CMD=0x%h", 
                         test_name, a, b, cmd);
                display_mismatch();
                fail_count = fail_count + 1;
            end
        end
    endtask

    // Compare DUT vs Reference
    function compare_outputs;
		input dummy;
        begin
            compare_outputs = 1;
            
            // Compare RES (handle Z values)
            if (RES_dut !== RES_ref) begin
                if (!((RES_dut === 9'bzzzzzzzzz) && (RES_ref === 9'bzzzzzzzzz)))
                    compare_outputs = 0;
            end
            
            // Compare flags (handle Z values)
            if (!compare_bit(COUT_dut, COUT_ref)) compare_outputs = 0;
            if (!compare_bit(OFLOW_dut, OFLOW_ref)) compare_outputs = 0;
            if (!compare_bit(G_dut, G_ref)) compare_outputs = 0;
            if (!compare_bit(E_dut, E_ref)) compare_outputs = 0;
            if (!compare_bit(L_dut, L_ref)) compare_outputs = 0;
            if (!compare_bit(ERR_dut, ERR_ref)) compare_outputs = 0;
        end
    endfunction

    // Compare single bit (handle Z)
    function compare_bit;
		input dut, ref;
        begin
            if (dut === ref)
                compare_bit = 1;
            else if ((dut === 1'bz) && (ref === 1'bz))
                compare_bit = 1;
            else
                compare_bit = 0;
        end
    endfunction

    // Display mismatch details
    task display_mismatch();
        begin
            $display("  DUT: RES=0x%h COUT=%b OFLOW=%b G=%b E=%b L=%b ERR=%b",
                     RES_dut, COUT_dut, OFLOW_dut, G_dut, E_dut, L_dut, ERR_dut);
            $display("  REF: RES=0x%h COUT=%b OFLOW=%b G=%b E=%b L=%b ERR=%b",
                     RES_ref, COUT_ref, OFLOW_ref, G_ref, E_ref, L_ref, ERR_ref);
        end
    endtask

    // Waveform dump
    initial begin
        $dumpfile("alu_test.vcd");
        $dumpvars(0, alu_testbench);
    end

endmodule

src/verification/alu_test.vcd
$date
	Fri May  8 11:44:28 2026
$end
$version
	QuestaSim Version 10.6c
$end
$timescale
	1ps
$end

$scope module alu_testbench $end
$var reg 8 ! OPA [7:0] $end
$var reg 8 " OPB [7:0] $end
$var reg 1 # CLK $end
$var reg 1 $ RST $end
$var reg 1 % CE $end
$var reg 1 & MODE $end
$var reg 1 ' CIN $end
$var reg 4 ( CMD [3:0] $end
$var wire 1 ) RES_dut [15] $end
$var wire 1 * RES_dut [14] $end
$var wire 1 + RES_dut [13] $end
$var wire 1 , RES_dut [12] $end
$var wire 1 - RES_dut [11] $end
$var wire 1 . RES_dut [10] $end
$var wire 1 / RES_dut [9] $end
$var wire 1 0 RES_dut [8] $end
$var wire 1 1 RES_dut [7] $end
$var wire 1 2 RES_dut [6] $end
$var wire 1 3 RES_dut [5] $end
$var wire 1 4 RES_dut [4] $end
$var wire 1 5 RES_dut [3] $end
$var wire 1 6 RES_dut [2] $end
$var wire 1 7 RES_dut [1] $end
$var wire 1 8 RES_dut [0] $end
$var wire 1 9 COUT_dut $end
$var wire 1 : OFLOW_dut $end
$var wire 1 ; G_dut $end
$var wire 1 < E_dut $end
$var wire 1 = L_dut $end
$var wire 1 > ERR_dut $end
$var wire 1 ? RES_ref [8] $end
$var wire 1 @ RES_ref [7] $end
$var wire 1 A RES_ref [6] $end
$var wire 1 B RES_ref [5] $end
$var wire 1 C RES_ref [4] $end
$var wire 1 D RES_ref [3] $end
$var wire 1 E RES_ref [2] $end
$var wire 1 F RES_ref [1] $end
$var wire 1 G RES_ref [0] $end
$var wire 1 H COUT_ref $end
$var wire 1 I OFLOW_ref $end
$var wire 1 J G_ref $end
$var wire 1 K E_ref $end
$var wire 1 L L_ref $end
$var wire 1 M ERR_ref $end
$var integer 32 N pass_count $end
$var integer 32 O fail_count $end
$var integer 32 P test_count $end
$var wire 1 Q INP_VALID $end

$scope task test_arithmetic $end
$upscope $end

$scope task test_logical $end
$upscope $end

$scope task apply_test $end
$var reg 8 R a [7:0] $end
$var reg 8 S b [7:0] $end
$var reg 4 T cmd [3:0] $end
$var reg 640 U test_name [640:1] $end
$upscope $end

$scope function compare_outputs $end
$var reg 1 V compare_outputs $end
$var reg 1 W dummy $end
$upscope $end

$scope function compare_bit $end
$var reg 1 X compare_bit $end
$var reg 1 Y dut $end
$var reg 1 Z ref $end
$upscope $end

$scope task display_mismatch $end
$upscope $end

$scope module dut $end
$var parameter 32 [ width $end
$var parameter 32 \ cmd_width $end
$var parameter 32 ] out_width $end
$var wire 1 ^ OPA [7] $end
$var wire 1 _ OPA [6] $end
$var wire 1 ` OPA [5] $end
$var wire 1 a OPA [4] $end
$var wire 1 b OPA [3] $end
$var wire 1 c OPA [2] $end
$var wire 1 d OPA [1] $end
$var wire 1 e OPA [0] $end
$var wire 1 f OPB [7] $end
$var wire 1 g OPB [6] $end
$var wire 1 h OPB [5] $end
$var wire 1 i OPB [4] $end
$var wire 1 j OPB [3] $end
$var wire 1 k OPB [2] $end
$var wire 1 l OPB [1] $end
$var wire 1 m OPB [0] $end
$var wire 1 n CLK $end
$var wire 1 o RST $end
$var wire 1 p CE $end
$var wire 1 q MODE $end
$var wire 1 r CIN $end
$var wire 1 s inp_valid [1] $end
$var wire 1 Q inp_valid [0] $end
$var wire 1 t CMD [3] $end
$var wire 1 u CMD [2] $end
$var wire 1 v CMD [1] $end
$var wire 1 w CMD [0] $end
$var reg 16 x RES [15:0] $end
$var reg 1 y COUT $end
$var reg 1 z OFLOW $end
$var reg 1 { G $end
$var reg 1 | E $end
$var reg 1 } L $end
$var reg 1 ~ ERR $end
$var reg 16 !! temp_signed [15:0] $end
$var reg 16 "! temp_res [15:0] $end
$var reg 1 #! temp_cout $end
$var reg 1 $! temp_oflow $end
$var reg 1 %! temp_g $end
$var reg 1 &! temp_e $end
$var reg 1 '! temp_l $end
$var reg 1 (! temp_err $end
$var reg 8 )! A_signed [7:0] $end
$var reg 8 *! B_signed [7:0] $end
$var integer 32 +! count $end
$var integer 32 ,! count1 $end
$upscope $end

$scope module ref $end
$var wire 1 -! CLK $end
$var wire 1 .! RST $end
$var wire 1 /! CE $end
$var wire 1 0! INP_VALID [1] $end
$var wire 1 Q INP_VALID [0] $end
$var wire 1 1! OPA [7] $end
$var wire 1 2! OPA [6] $end
$var wire 1 3! OPA [5] $end
$var wire 1 4! OPA [4] $end
$var wire 1 5! OPA [3] $end
$var wire 1 6! OPA [2] $end
$var wire 1 7! OPA [1] $end
$var wire 1 8! OPA [0] $end
$var wire 1 9! OPB [7] $end
$var wire 1 :! OPB [6] $end
$var wire 1 ;! OPB [5] $end
$var wire 1 <! OPB [4] $end
$var wire 1 =! OPB [3] $end
$var wire 1 >! OPB [2] $end
$var wire 1 ?! OPB [1] $end
$var wire 1 @! OPB [0] $end
$var wire 1 A! CIN $end
$var wire 1 B! MODE $end
$var wire 1 C! CMD [3] $end
$var wire 1 D! CMD [2] $end
$var wire 1 E! CMD [1] $end
$var wire 1 F! CMD [0] $end
$var reg 17 G! RES [16:0] $end
$var reg 1 H! COUT $end
$var reg 1 I! OFLOW $end
$var reg 1 J! G $end
$var reg 1 K! E $end
$var reg 1 L! L $end
$var reg 1 M! ERR $end
$var reg 8 N! OPA_1 [7:0] $end
$var reg 8 O! OPB_1 [7:0] $end
$upscope $end
$upscope $end
$enddefinitions $end
#0
$dumpvars
b0 !
b0 "
0#
1$
0%
0&
0'
b0 (
b0 x
0y
0z
0{
0|
0}
0~
b0 !!
b0 "!
0#!
0$!
0%!
0&!
0'!
1(!
b0 )!
b0 *!
b0 G!
0H!
0I!
0J!
0K!
0L!
0M!
bx N!
bx O!
bx R
bx S
bx T
bx U
xV
xW
xX
xY
xZ
b1000 [
b100 \
b10000 ]
b0 N
b0 O
b0 P
b1 +!
b1 ,!
08
07
06
05
04
03
02
01
00
0/
0.
0-
0,
0+
0*
0)
09
0:
0;
0<
0=
0>
0G
0F
0E
0D
0C
0B
0A
0@
0?
0H
0I
0J
0K
0L
0M
zQ
0F!
0E!
0D!
0C!
0B!
0A!
0@!
0?!
0>!
0=!
0<!
0;!
0:!
09!
08!
07!
06!
05!
04!
03!
02!
01!
0/!
1.!
0-!
0w
0v
0u
0t
0r
0q
0p
1o
0n
0m
0l
0k
0j
0i
0h
0g
0f
0e
0d
0c
0b
0a
0`
0_
0^
zs
z0!
$end
#5000
1#
1-!
1n
0$
1%
1p
0o
0.!
1/!
#10000
0#
0-!
0n
#15000
1#
1-!
1n
1&
b1111 R
b10001 S
b0 T
b10000010100010001000100 U
1q
1B!
0(!
1(!
1~
1>
#20000
0#
0-!
0n
#25000
1#
1-!
1n
b1111 !
b10001 "
1@!
1<!
1m
1i
18!
17!
16!
15!
1e
1d
1c
1b
0(!
1(!
b100000 G!
1B
#30000
0#
0-!
0n
#35000
1#
1-!
1n
#40000
0#
0-!
0n
#45000
1#
1-!
1n
b1 P
0W
1V
0V
0Y
0Z
1X
1Y
0X
b1 O
b11111111 R
b1 S
b100000101000100010001000010000000101000011011110111011001100101011100100110011001101100011011110111011100101001 U
#50000
0#
0-!
0n
#55000
1#
1-!
1n
b11111111 !
b1 "
0<!
0i
14!
13!
12!
11!
1a
1`
1_
1^
0(!
1(!
b0 G!
1H!
0B
1H
#60000
0#
0-!
0n
#65000
1#
1-!
1n
#70000
0#
0-!
0n
#75000
1#
1-!
1n
b10 P
1V
0Y
1Z
0V
0Z
1X
1Y
0X
b10 O
b100000 R
b10000 S
b1 T
b10100110101010101000010 U
#80000
0#
0-!
0n
#85000
1#
1-!
1n
b100000 !
b10000 "
b1 (
1F!
1w
0@!
1<!
0m
1i
08!
07!
06!
05!
04!
02!
01!
0e
0d
0c
0b
0a
0_
0^
0(!
1(!
0H!
b10000 G!
0H
1C
#90000
0#
0-!
0n
#95000
1#
1-!
1n
#100000
0#
0-!
0n
#105000
1#
1-!
1n
b11 P
1V
0V
0Y
1X
1Y
0X
b11 O
b10000 R
b100000 S
b10100110101010101000010001000000010100001110101011011100110010001100101011100100110011001101100011011110111011100101001 U
#110000
0#
0-!
0n
#115000
1#
1-!
1n
b10000 !
b100000 "
0<!
1;!
0i
1h
14!
03!
1a
0`
0(!
1(!
b0 G!
1I!
b11111111111110000 G!
1B
1A
1@
1?
1I
#120000
0#
0-!
0n
#125000
1#
1-!
1n
#130000
0#
0-!
0n
#135000
1#
1-!
1n
b100 P
1V
0V
0Y
1X
1Z
0X
0Z
1X
1Y
0X
b100 O
1'
b10 T
b1000001010001000100010001011111010000110100100101001110 U
1r
1A!
b0 G!
0I!
1I!
b11111111111110000 G!
0(!
1(!
#140000
0#
0-!
0n
#145000
1#
1-!
1n
b10 (
0F!
1E!
0w
1v
0(!
1(!
b0 G!
0I!
b110001 G!
1G
0A
0@
0?
0I
#150000
0#
0-!
0n
#155000
1#
1-!
1n
#160000
0#
0-!
0n
#165000
1#
1-!
1n
b101 P
1V
0V
0Y
1X
1Y
0X
b101 O
0'
b1010 R
b0 S
b100 T
b100100101001110010000110101111101000001 U
0r
0A!
b0 G!
b110000 G!
0(!
1(!
0G
#170000
0#
0-!
0n
#175000
1#
1-!
1n
b1010 !
b0 "
b100 (
0E!
1D!
0v
1u
0;!
0h
17!
15!
04!
1d
1b
0a
0(!
1(!
b0 G!
b1011 G!
1G
1F
1D
0C
0B
#180000
0#
0-!
0n
#185000
1#
1-!
1n
#190000
0#
0-!
0n
#195000
1#
1-!
1n
b110 P
1V
0V
0Y
1X
1Y
0X
b110 O
b101 T
b100010001000101010000110101111101000001 U
#200000
0#
0-!
0n
#205000
1#
1-!
1n
b101 (
1F!
1w
0(!
1(!
b0 G!
b1001 G!
0F
#210000
0#
0-!
0n
#215000
1#
1-!
1n
#220000
0#
0-!
0n
#225000
1#
1-!
1n
b111 P
1V
0V
0Y
1X
1Y
0X
b111 O
b10000 R
b10000 S
b1000 T
b100001101001101010100000010000000101000011001010111000101110101011000010110110000101001 U
#230000
0#
0-!
0n
#235000
1#
1-!
1n
b10000 !
b10000 "
b1000 (
0F!
0D!
1C!
0w
0u
1t
1<!
1i
07!
05!
14!
0d
0b
1a
0(!
1(!
b0 G!
b0zzzzzzzzz G!
1K!
zG
zF
zE
zD
zC
zB
zA
z@
z?
1K
#240000
0#
0-!
0n
#245000
1#
1-!
1n
#250000
0#
0-!
0n
#255000
1#
1-!
1n
b1000 P
1V
0V
0Y
1X
1Z
0X
0Z
1X
1Y
0X
b1000 O
b100000 R
b1000011010011010101000000100000001010000110011101110010011001010110000101110100011001010111001000101001 U
#260000
0#
0-!
0n
#265000
1#
1-!
1n
b100000 !
04!
13!
0a
1`
0(!
1(!
b0 G!
0K!
b0zzzzzzzzz G!
1J!
0K
1J
#270000
0#
0-!
0n
#275000
1#
1-!
1n
#280000
0#
0-!
0n
#285000
1#
1-!
1n
b1001 P
1V
0V
0Y
1X
1Z
0X
0Z
1X
1Y
0X
b1001 O
b10000 R
b100000 S
b1000011010011010101000000100000001010000110110001100101011100110111001100101001 U
#290000
0#
0-!
0n
#295000
1#
1-!
1n
b10000 !
b100000 "
0<!
1;!
0i
1h
14!
03!
1a
0`
0(!
1(!
b0 G!
0J!
b0zzzzzzzzz G!
1L!
0J
1L
#300000
0#
0-!
0n
#305000
1#
1-!
1n
#310000
0#
0-!
0n
#315000
1#
1-!
1n
b1010 P
1V
0V
0Y
1X
1Z
0X
1Y
0Z
b1010 O
0&
b11110000 R
b1111 S
b0 T
b10000010100111001000100 U
0q
0B!
b0 G!
0L!
b1000 G!
0(!
1(!
0G
0F
0E
1D
0C
0B
0A
0@
0?
0L
#320000
0#
0-!
0n
#325000
1#
1-!
1n
b11110000 !
b1111 "
b0 (
0C!
0t
1@!
1?!
1>!
1=!
0;!
1m
1l
1k
1j
0h
13!
12!
11!
1`
1_
1^
0(!
1(!
b0 G!
0D
#330000
0#
0-!
0n
#335000
1#
1-!
1n
#340000
0#
0-!
0n
#345000
1#
1-!
1n
b1011 P
1V
0Y
1X
1Y
0X
0V
b1011 O
b1 T
b1001110010000010100111001000100 U
#350000
0#
0-!
0n
#355000
1#
1-!
1n
b1 (
1F!
1w
0(!
1(!
b11111111 G!
1G
1F
1E
1D
1C
1B
1A
1@
#360000
0#
0-!
0n
#365000
1#
1-!
1n
#370000
0#
0-!
0n
#375000
1#
1-!
1n
b1100 P
1V
0V
0Y
1X
1Y
0X
b1100 O
b10 T
b100111101010010 U
#380000
0#
0-!
0n
#385000
1#
1-!
1n
b10 (
0F!
1E!
0w
1v
0(!
1(!
b0 G!
b11111111 G!
#390000
0#
0-!
0n
#395000
1#
1-!
1n
#400000
0#
0-!
0n
#405000
1#
1-!
1n
b1101 P
1V
0V
0Y
1X
1Y
0X
b1101 O
b11 T
b10011100100111101010010 U
#410000
0#
0-!
0n
#415000
1#
1-!
1n
b11 (
1F!
1w
0(!
1(!
b0 G!
0G
0F
0E
0D
0C
0B
0A
0@
#420000
0#
0-!
0n
#425000
1#
1-!
1n
#430000
0#
0-!
0n
#435000
1#
1-!
1n
b1110 P
1V
0Y
1X
1Y
0X
0V
b1110 O
b10101010 R
b1010101 S
b100 T
b10110000100111101010010 U
#440000
0#
0-!
0n
#445000
1#
1-!
1n
b10101010 !
b1010101 "
b100 (
0F!
0E!
1D!
0w
0v
1u
0?!
0=!
1<!
1:!
0l
0j
1i
1g
17!
15!
04!
02!
1d
1b
0a
0_
0(!
1(!
b11111111 G!
1G
1F
1E
1D
1C
1B
1A
1@
#450000
0#
0-!
0n
#455000
1#
1-!
1n
#460000
0#
0-!
0n
